qbee/__init__.py
qbee/dimension_agnostic.py
qbee/experimental/__init__.py
qbee/experimental/numerical.py
qbee/experimental/pde.py
qbee/no_C4_count.py
qbee/polynomialization.py
qbee/printer.py
qbee/quadratization.py
qbee/selection.py
qbee/util.py
qbee-0.8.2.dist-info/entry_points.txt
qbee-0.8.2.dist-info/LICENSE
qbee-0.8.2.dist-info/METADATA
qbee-0.8.2.dist-info/WHEEL
qbee-0.8.2.dist-info/RECORD
