Metadata-Version: 2.1
Name: qbee
Version: 0.8.2
Summary: Quadratization of differential equations in python
License: MIT
Author: Andrey Bychkov, Gleb Pogudin
Requires-Python: >=3.8,<4.0
Classifier: License :: OSI Approved :: MIT License
Classifier: Programming Language :: Python :: 3
Classifier: Programming Language :: Python :: 3.8
Classifier: Programming Language :: Python :: 3.9
Classifier: Programming Language :: Python :: 3.10
Classifier: Programming Language :: Python :: 3.11
Requires-Dist: matplotlib (>=3.6.2,<4.0.0)
Requires-Dist: memory_profiler
Requires-Dist: numpy (>=1,<2)
Requires-Dist: ordered-set
Requires-Dist: pandas (>=1,<2)
Requires-Dist: pyarrow (>=10,<11)
Requires-Dist: pygal (>=3.0.0,<4.0.0)
Requires-Dist: scipy (>=1,<2)
Requires-Dist: sympy (>=1.5.0,<2.0.0)
Requires-Dist: tqdm (>=4,<5)
